<?xml version="1.0" encoding="utf-8"?>

<!DOCTYPE report [
  <!ENTITY s SYSTEM ".\Include\Separate.xml">
  <!ENTITY p "../images/pdf.gif">
  <!ENTITY e "../images/excel.gif">
]>

<report xmlns="urn:schemas-ai-erp:data-report">
  <forms>
    <form id="010" reportFile="hrptRewardList_01" commandArgument="pdf" urlImage="&p;">
      <header v="Danh sách khen thưởng nhân viên" e="Award Recipients"></header>
      <download>
        <header v="Danh sách khen thưởng nhân viên" e="Award Recipients"></header>
      </download>
    </form>

    &s;

    <form id="110" templateFile ="hrptRewardList_01" commandArgument="Excel" urlImage="&e;">
      <header v="Danh sách khen thưởng nhân viên" e="Award Recipients"/>
      <download>
        <header v="Danh sách khen thưởng nhân viên" e="Award Recipients"/>
      </download>
    </form>
  </forms>

  <fields>
    <field name="title" type="String">
      <header v="DANH SÁCH KHEN THƯỞNG NHÂN VIÊN" e="AWARD RECIPIENTS"/>
    </field>
    <field name="h_ngay_kt1" type="String">
      <header v="Từ ngày" e="Reward Date from"/>
    </field>
    <field name="h_ngay_kt2" type="String">
      <header v="đến ngày" e="to"/>
    </field>
    <field name="h_tu_ngay2" type="String">
      <header v="Từ ngày:" e="Award Date from:"/>
    </field>
    <field name="h_den_ngay2" type="String">
      <header v="Đến ngày:" e="Award Date to:"/>
    </field>
    <field name="h_stt" type="String">
      <header v="Stt" e="No."/>
    </field>
    <field name="h_ma_nv" type="String">
      <header v="Mã nhân viên" e="Employee ID"/>
    </field>
    <field name="h_ten_nv" type="String">
      <header v="Họ và tên nhân viên" e="Employee Full Name"/>
    </field>
    <field name="h_bp" type="String">
      <header v="Bộ phận" e="Department"/>
    </field>
    <field name="h_vtr" type="String">
      <header v="Vị trí công việc" e="Position"/>
    </field>
    <field name="h_ngay_vao" type="String">
      <header v="Ngày vào cty" e="Date in"/>
    </field>
    <field name="h_ttnv" type="String">
      <header v="Tình trạng" e="Status"/>
    </field>
    <field name="h_loai_kt" type="String">
      <header v="Loại khen thưởng" e="Award"/>
    </field>
    <field name="h_ngay_kt" type="String">
      <header v="Ngày khen thưởng" e="Date of Award"/>
    </field>
    <field name="h_ly_do" type="String">
      <header v="Lý do khen thưởng" e="Reason"/>
    </field>
    <field name="h_gioi_tinh" type="String">
      <header v="Giới tính" e="Gender"/>
    </field>
  </fields>
</report>