<?xml version="1.0" encoding="utf-8"?>

<!DOCTYPE report [
  <!ENTITY s SYSTEM ".\Include\Separate.xml">
  <!ENTITY p "../images/pdf.gif">
  <!ENTITY e "../images/excel.gif">
]>

<report xmlns="urn:schemas-ai-erp:data-report">
  <forms>
    <form id="010" reportFile="hrptRMApplicantProfile_01" commandArgument="Pdf" urlImage="&p;">
      <header v="Báo cáo hồ sơ ứng viên" e="Applicant Profiles"/>
      <download>
        <header v="Báo cáo hồ sơ ứng viên" e="Applicant Profiles"/>
      </download>
    </form>

    &s;

    <form id="110" templateFile="hrptRMApplicantProfile_01" commandArgument="Excel" urlImage="&e;">
      <header v="Báo cáo hồ sơ ứng viên" e="Applicant Profiles"/>
      <download>
        <header v="Báo cáo hồ sơ ứng viên" e="Applicant Profiles"/>
      </download>
    </form>
  </forms>

  <fields>
    <field name="title" type="String">
      <header v="BÁO CÁO HỒ SƠ ỨNG VIÊN" e="APPLICANT PROFILES"/>
    </field>
    <field name="h_tu_ngay" type ="String">
      <header v="Ngày nộp hồ sơ từ" e="Date Applied from"/>
    </field>
    <field name="h_den_ngay" type="String">
      <header v="đến ngày" e="to"/>
    </field>
    <field name="h_den_ngay2" type="String">
      <header v="Ngày nộp hồ sơ đến" e="Date Applied to"/>
    </field>
    <field name="h_stt" type="String">
      <header v="Stt" e="No."/>
    </field>
    <field name="h_ma_uv" type="String">
      <header v="Mã ứng viên" e="Applicant ID"/>
    </field>
    <field name="h_ho_ten_uv" type="String">
      <header v="Họ và tên" e="Full Name"/>
    </field>
    <field name="h_ngay_sinh" type="String">
      <header v="Ngày sinh" e="Date of Birth"/>
    </field>
    <field name="h_gioi_tinh" type="String">
      <header v="Giới tính" e="Gender"/>
    </field>
    <field name="h_vi_tri" type="String">
      <header v="Vị trí" e="Vacancy"/>
    </field>
    <field name="h_bo_phan" type="String">
      <header v="Bộ phận" e="Department"/>
    </field>
    <field name="h_ngay_hs" type="String">
      <header v="Ngày nộp hồ sơ" e="Date Applied"></header>
    </field>
    <field name="h_trang_thai" type="String">
      <header v="Trạng thái hồ sơ" e="Status"/>
    </field>

    <field name="h_ma_dot">
      <header v="Mã đợt" e="Period Code"></header>
    </field>
    <field name="h_ten_dot">
      <header v="Tên đợt tuyển dụng" e="Recruitment Period Name"/>
    </field>
  </fields>
</report>